lckytools/__init__.py
lckytools/__main__.py
lckytools/airflow/__init__.py
lckytools/airflow/const.py
lckytools/geo/__init__.py
lckytools/geo/distance.py
lckytools/sql/__init__.py
lckytools/sql/fetch.py
lckytools/sql/schema.py
lckytools/sql/table.py
lckytools-0.0.22.dist-info/LICENSE
lckytools-0.0.22.dist-info/METADATA
lckytools-0.0.22.dist-info/WHEEL
lckytools-0.0.22.dist-info/top_level.txt
lckytools-0.0.22.dist-info/RECORD
