Metadata-Version: 2.1
Name: lckytools
Version: 0.0.22
Author-email: LCKYN <t.pwawrit@lckyn.com>
License: MIT License
Project-URL: homepage, https://github.com/LCKYN/LckyTools
Keywords: lckytools,pandas,sql,dataframe2sql
Classifier: Development Status :: 1 - Planning
Classifier: License :: OSI Approved :: MIT License
Classifier: Programming Language :: Python :: 3
Classifier: Programming Language :: Python :: 3.8
Classifier: Programming Language :: Python :: 3.9
Classifier: Programming Language :: Python :: 3 :: Only
Classifier: Topic :: Software Development :: Libraries :: Python Modules
Classifier: Topic :: Utilities
Requires-Python: >=3.8
License-File: LICENSE
Requires-Dist: pandas
